{"application":{"進入區域":"插天山自然保留區","申請編號":"R10605353","&nbsp;":"&nbsp;","密碼":"43867","申請日期":"2017\/11\/8","申請人":"邱薇靜","進入期間":"2017\/11\/25 &nbsp;~&nbsp;2017\/11\/25","進入目的":"相關團體為環境教育之需要","檔案上傳":"","EMail":"green90122@gmail.com","進入範圍":"東眼山森林遊樂區至北插天山步道沿線","到達入口時間":"08:00","進入入口及出口地點":"東眼山森林遊樂區\/折返回東眼山森林遊樂區","狀態":"申請核准","每日行程路線":"8:00東眼山森林遊樂區→9：30東滿步道→11：00東滿、北插叉路口→11：50水源地→12：30木屋遺址→13：50北插天山→16:00水源地→16：50東滿步道→18：00東眼山","環境維護措施":"1.全體隊員遵守進入管制規定及無痕山林規範2.不隨意離開已開放供使用之步道及區域3.除了攝影，不帶走任何物品，不留下垃圾4.由領隊進行環境教育解說","緊急災難處理":"1.裝備：地圖、手機、小刀、頭燈、手電筒、備用電池、急救包2.撤退方式：如身體不適或天氣變化或路線受阻，立即原路撤退下山"},"members":[["1","邱薇靜","N224924814","&nbsp;","76-11-03","新北市板橋區中山路二段148巷6號2樓","0989913293"," 邱顯權 "," 0965396133 "],["2","邱伃君","N224811536","&nbsp;","75-04-25","新北市板橋區中山路二段148巷6號2樓","0913251132"," 邱顯權 "," 0965396133 "],["3","邱奕憲","N125237658","&nbsp;","79-03-18","桃園市八德區仁德路76號3樓","0979185431"," 邱顯權 "," 0965396133 "]]}