{"application":{"進入區域":"插天山自然保留區","申請編號":"R10605880","&nbsp;":"&nbsp;","密碼":"31467","申請日期":"2017\/12\/1","申請人":"段基文","進入期間":"2018\/1\/21 &nbsp;~&nbsp;2018\/1\/21","進入目的":"相關團體為環境教育之需要","檔案上傳":"","EMail":"cwtuan@nuvoton.com","進入範圍":"滿月圓森林遊樂區至北插天山步道沿線","到達入口時間":"09:00","進入入口及出口地點":"小烏來第二停車場","狀態":"抽籤未中","每日行程路線":"0910 小烏來第二停車場出發0945 威赫山1105 水源地1120 木屋遺址，陡升攀爬的開始1315 北插天山 1727M1440 木屋遺址 (含吃飯時間)1518 水源地1637 小烏來停車場","環境維護措施":"1. 全體隊員遵守進入管制規定及無痕山林規範。2. 不隨意離開已開放供使用之步道及區域。3. 在體驗大自然的豐富饗宴之餘，除了攝影，不帶走任何物品；除了回憶，不留下任何垃圾。4. 由領隊進行環境教育解說。","緊急災難處理":"1. 裝備：GPS, 手機2. 保險：200萬意外，20萬意外醫療3. 留守人員姓名：AAA、連絡電話：4. 撤退方式：如身體不適或天氣變化或路線受阻，立即原路撤退下山"},"members":[["1","段基文","R120604223","&nbsp;","51-11-15","新竹市東區大學路81巷3弄2號1樓","0973-250622"," 段宛萱 "," 0963-266488 "],["2","黃錦信","J121277260","&nbsp;","51-08-26","新竹縣新豐鄉中崙村2鄰35-14號","0937-031622"," 陳金瑛 "," 03-5903082 "],["3","廖伊雯","K220295927","&nbsp;","65-07-02","台中市豐原區圓環北路一段44號","0972-694290"," 王彩雪 "," 0972-372290 "],["4","陳玉玲","J221857064","&nbsp;","68-08-05","苗栗縣頭份鎮信東路2段258巷15號","0930-966013"," 康仁和 "," 0972-828586 "],["5","蔡文月","J220242292","&nbsp;","63-11-05","新竹市北區尚濱路70號6F~1","0911-216910"," 蔡錦清 "," 0918-375777 "],["6","林志翰","V121434372","&nbsp;","68-06-20","新竹縣竹北市自強南路59巷１號10F-7","0933-598340"," 林俐君 "," 0912-285358 "],["7","藍心伶","J290008979","&nbsp;","65-12-02","新竹縣北埔鄉南埔村3鄰28之2號","0926-738198"," 李永清 "," 0926-738163 "],["8","陳威宇","O100074540","&nbsp;","73-10-08","新竹市培英街31號三樓","0989-522490"," 陳淦銘 "," 0917-211827 "],["9","邱定同","H121414468","&nbsp;","55-06-05","新埔鎮中正路53巷36號","0928-070740"," 邱渝靜 "," 0975-550811 "],["10","陳斌欣","V121028249","&nbsp;","68-03-29","新北市中和區莊敬路49巷20弄22號5樓","0919-128231"," 陳儷云 "," 0928-558005 "],["11","李惠英","C220716979","&nbsp;","63-11-25","新竹市科學園區力行六路10號","0961-155661"," 李珍 "," 0939-139800 "],["12","曾淑鈴","Q221587240","&nbsp;","66-09-13","新北市五股區中興路一段150巷23號","0912-728877"," 曾柯玉里 "," 0919-981993 "],["13","王俐茹","A224728795","&nbsp;","67-03-24","台北市中山區民生東路一段88號8樓之3","0955-843219"," 楊秀珠 "," 0918-587699 "],["14","陳宏裕","B121529431","&nbsp;","67-07-29","台中市重慶路443號","0955-973497"," 陳炳輝 "," 0930-983923 "],["15","蔡幸君","A224203177","&nbsp;","67-10-11","新北市三重區集美街89巷11號1樓","0920-062580"," 許淑芬(母) "," 02-29772920 "]]}