{"application":{"進入區域":"苗栗三義火炎山自然保留區","申請編號":"R10700009","&nbsp;":"&nbsp;","密碼":"38525","申請日期":"2018\/1\/1","申請人":"徐培文","進入期間":"2018\/1\/27 &nbsp;~&nbsp;2018\/1\/27","進入目的":"相關團體為環境教育之需要","檔案上傳":"","EMail":"kevin90969@msn.com","進入範圍":"火炎山自然保留區內","到達入口時間":"08:00","進入入口及出口地點":"入口台13線55.3公里的高架橋下\/出口南鞍古道接產業道路","狀態":"申請核准","每日行程路線":"登山口→休憩區→火炎山三角點→返回休憩區→南鞍古道→產業道路→登山口","環境維護措施":"遵守入山規定並不留下任何垃圾","緊急災難處理":"1.下雨則取消2.留守人員：徐培慈、0921225499"},"members":[["1","徐培文","E123964646","&nbsp;","76-10-08","高雄市苓雅區武營路449巷28號","0988021579"," 徐培慈 "," 0921225499 "],["2","徐宗明","T100632027","&nbsp;","41-09-11","高雄市苓雅區武營路449巷28號","0937378807"," 徐培慈 "," 0921225499 "],["3","李忠杰","S123543479","&nbsp;","77-01-12","高雄市鳳山區光明路34巷12-1號","0916473691"," 楊美香 "," 0929199869 "]]}