{"application":{"進入區域":"插天山自然保留區","申請編號":"R10700148","&nbsp;":"&nbsp;","密碼":"58162","申請日期":"2018\/1\/5","申請人":"陳世玄","進入期間":"2018\/2\/11 &nbsp;~&nbsp;2018\/2\/11","進入目的":"相關團體為環境教育之需要","檔案上傳":"","EMail":"f8386504@gmail.com","進入範圍":"東眼山森林遊樂區至北插天山步道沿線","到達入口時間":"08:00","進入入口及出口地點":"東眼山森林遊樂區\/東眼山森林遊樂區","狀態":"備取失敗（順序：3）","每日行程路線":"08:00東眼山→1100水源地→1110木屋遺址→1300插天山→1400木屋遺址→1410水源地→1630東眼山","環境維護措施":"1.全體隊員遵守進入管制規定及無痕山林規範。2.不隨意離開已開放供使用之步道及區域。3.在體驗大自然的豐富饗宴之餘，除了攝影，不帶走任何物品；除了回憶，不留下任何垃圾。4.由領隊進行環境教育解說。","緊急災難處理":"1.裝備:地圖、指北針、手機、急救包、登山GPS、通訊設備:手機數支。2.保險:200萬意外、20萬意外醫療，保險其間:1月2705:00時~1月28日05:00時。3.留守人員姓名:葉美智、聯絡電話:09108171314.撤退方式:如有身體不適或天氣變化或路線受阻，立即爰路撤退下山，選擇滿月園路線撤退。"},"members":[["1","陳世玄","F123778838","&nbsp;","65-04-08","新北市永和區保平路236巷15弄1號4樓","0953312450"," 葉美智 "," 0910817131 "],["2","張吉村","H124700381","&nbsp;","57-02-18","桃園市龜山區樂宮街9號","0988399218"," 張秀枝 "," 0915942071 "],["3","黃致維","H120088544","&nbsp;","63-03-17","桃園市桃園區秀山路86巷2號","0926080577"," 張沛涵 "," 0953590329 "]]}