{"application":{"進入區域":"插天山自然保留區","申請編號":"R10605257","&nbsp;":"&nbsp;","密碼":"63618","申請日期":"2017\/11\/4","申請人":"高嘉宏","進入期間":"2017\/11\/27 &nbsp;~&nbsp;2017\/11\/27","進入目的":"相關團體為環境教育之需要","檔案上傳":"","EMail":"u910601@gmail.com","進入範圍":"小烏來登山口至北插天山步道沿線","到達入口時間":"07:30","進入入口及出口地點":"出入:小烏來第二登山口","狀態":"申請核准","每日行程路線":"07:30 小烏來第二登山口-->10:00 水源地-->10:30 木屋遺址-->13:30北插天山-->15:30 木屋遺址-->15:45 水源地-->17:00 小烏來第二登山口 ; 從事探查自然環境。","環境維護措施":"1.全體隊員遵守進入管制區規定即無痕山林規範。2.不隨意離開已開放供使用之步道及區域。3.在體驗大自然的豐富饗宴之餘，除了攝影不帶走任何物品，不留下任何垃圾。","緊急災難處理":"地圖、頭燈、雨衣、手機、行動電源 等必要之登山器材。每人投保200萬意外險20萬醫療險，保險期間；11\/27\/ 07:00~1800留守人員:王俊憲 手機0988698009如有人員不適或天氣變化道路損壞則立即下撤"},"members":[["1","高嘉宏","D122035903","&nbsp;","73-12-12","新北市三重區重陽路一段123號","0952-830-337"," 高林春花 "," 0921-217607 "],["2","蔡芳儀","F225426973","&nbsp;","71-11-08","新北市新莊區中信街37巷1弄6號3樓","(02)-2993-3867"," 吳佳珊 "," 0935-238008 "],["3","丁永歡","E224228794","&nbsp;","78-10-18","台北市信義區松信路103號4樓","0922-781018"," 丁永強 "," 0952-511569 "],["4","蔡銘倫","G121802323","&nbsp;","74-11-27","宜蘭縣頭城鎮青雲路二段442號","0937-908541"," 蔡文琛 "," 03-977-5073 "]],"reviewed":{"check_note":""},"attachment":[]}