{"application":{"進入區域":"插天山自然保留區","申請編號":"R10606544","&nbsp;":"&nbsp;","密碼":"64475","申請日期":"2017\/12\/29","申請人":"廖佳麟","進入期間":"2018\/1\/20 &nbsp;~&nbsp;2018\/1\/20","進入目的":"相關團體為環境教育之需要","檔案上傳":"","EMail":"jugi0000@hotmail.com","進入範圍":"烏來至北插天山步道沿線","到達入口時間":"07:00","進入入口及出口地點":"小烏來登山口","狀態":"抽籤未中","每日行程路線":"0700:小烏來登山口 -> 1000:水源地 -> 1200:插天山 -> 1430:水源地 -> 1730:小烏來登山口","環境維護措施":"1.全體隊員遵守進入管制和無痕山林規範2.自備垃圾袋等工具, 確保不留下垃圾,","緊急災難處理":"1. 攜帶地圖, 指北針, 手機等必要工具2. 攜帶雨具及食物及保暖衣物3. 必要時將視天候和隊員狀況是否撤退 （依原路撤退）4. 出發前告知家人或友人此行行程"},"members":[["1","廖佳麟","F125519293","&nbsp;","71-04-18","鶯歌區中正三路171巷5號5F","0931229163"," 洪翠娥 "," (02)26792803 "],["2","劉駿馨","F125162472","&nbsp;","71-02-01","三峽區中園街136號1F","0922595330"," 游鎮安 "," 0917189299 "],["3","陳榮駿","A126156222","&nbsp;","71-07-15","三峽區中園街136號1F","0919909528"," 游鎮安 "," 0917189299 "],["4","紀明輝","R123161930","&nbsp;","72-05-31","鶯歌區中正三路171巷5號5F","02-26792803"," 游鎮安 "," 0917189299 "]],"reviewed":{"check_note":""},"attachment":[]}