{"application":{"進入區域":"插天山自然保留區","申請編號":"R10606566","&nbsp;":"&nbsp;","密碼":"18883","申請日期":"2017\/12\/29","申請人":"陳建辰","進入期間":"2018\/1\/16 &nbsp;~&nbsp;2018\/1\/16","進入目的":"相關團體為環境教育之需要","檔案上傳":"","EMail":"irene1991716@yahoo.com.tw","進入範圍":"林班地範圍內","到達入口時間":"12:00","進入入口及出口地點":"小烏來第2登山口","狀態":"申請核准","每日行程路線":"07:00小烏來登山口起登09:00神木區10:00木屋遺址12;30插天山15:00木屋遺址17:00登山口","環境維護措施":"遵守管制區之所有規範 除了回憶不留下任何不相干物品","緊急災難處理":"1.裝備.地圖.GPS.手機.指北針2.留守人員吳宜庭 電話02-230926233.撤退方式:身体不適立即原路撤回"},"members":[["1","陳建辰","Q123379413","&nbsp;","72-07-24","北市萬華區寶興街140巷45號3樓","0908706321"," 吳宜庭 "," 0935201845 "],["2","陳宜惠","A226537069","&nbsp;","80-07-16","北市萬華區寶興街140巷45號3樓","0973716108"," 吳宜庭 "," 0935201845 "],["3","陳宜雯","A226815460","&nbsp;","78-02-10","北市萬華區寶興街140巷45號3樓","0223092623"," 吳宜庭 "," 0935201845 "]],"reviewed":{"check_note":""},"attachment":[]}