{"application":{"進入區域":"插天山自然保留區","申請編號":"R10605916","&nbsp;":"&nbsp;","密碼":"58341","申請日期":"2017\/12\/3","申請人":"曹國樑","進入期間":"2017\/12\/21 &nbsp;~&nbsp;2017\/12\/21","進入目的":"相關團體為環境教育之需要","檔案上傳":"","EMail":"ruast@hotmail.com.tw","進入範圍":"小烏來第二登山口至北插天山步道沿線","到達入口時間":"07:30","進入入口及出口地點":"入口 : 小烏來第二登山口 , 出口 : 小烏來第一登山口","狀態":"申請核准","每日行程路線":"登山路線及起止時間 : 0730時由小烏來第二登山口啟登-->赫威山-->水源地-->木屋遺址-->南北插叉路口-->北插天山-->木屋遺址-->赫威神木群-->小烏來第一登山口Ｏ型連走於1600時出山.","環境維護措施":"1.遵守管制規定及無痕山林規範. 2.除了攝影,不帶走任何物品;除了回憶,不留下任何垃圾.(垃圾自行打包下山) 3.不攀折任何林木花草,不驚擾任何蟲魚鳥獸.","緊急災難處理":"攜帶裝備:身分證,入山證,飲水,行動糧,護膝,登山杖,雨衣,防寒衣物,手電筒,手套,手機,充電器及線,背包及套. 備案:啟登後二小時內遇雨或霧即折返棄登. 登山及撤退路線:小烏來第二登山口-->赫威山-->水源地-->木屋遺址-->南北插叉路口-->北插天山-->木屋遺址-->赫威神木群-->小烏來第一登山口."},"members":[["1","曹國樑","E101452058","&nbsp;","45-02-15","新北市永和區永元路69巷7號5樓","0911-316645"," 曹雲 "," 0911-012875 "],["2","宋思文","P220348828","&nbsp;","47-10-14","新北市永和區永元路69巷7號5樓","0911-012657"," 曹雲 "," 0911-012875 "],["3","曹陽","F127634015","&nbsp;","79-01-20","新北市永和區永元路69巷7號5樓","0911-372566"," 曹雲 "," 0911-012875 "]],"reviewed":{"check_note":""},"attachment":[]}