{"application":{"進入區域":"苗栗三義火炎山自然保留區","申請編號":"R10700624","&nbsp;":"&nbsp;","密碼":"74275","申請日期":"2018\/1\/30","申請人":"連朱建霖","進入期間":"2018\/2\/19 &nbsp;~&nbsp;2018\/2\/19","進入目的":"相關團體為環境教育之需要","檔案上傳":"2018-01-30-22-25-19-2101061624.xls","EMail":"amd630521@gmail.com","進入範圍":"C火炎山自然保留區步道","到達入口時間":"08:00","進入入口及出口地點":"中山高三義交流道下轉台13南下約4.6K右線向下轉往140縣道，在高速公路橋墩第P3-4號旁","狀態":"申請取消","每日行程路線":"2\/19 08: 00登山口--50分--圍石休息站--70分--火炎山南鞍--10分--火炎山--10分--南鞍--50分--伯公坑--5分--登山口。O形環走純計步程約3-3.5小時。預計連停留下山時間為14:00","環境維護措施":"1.全隊遵守森林保育觀念,絕不違反各項規定2.所有廢棄物一律自行攜帶下山3回程參訪火炎山自然生態教育館","緊急災難處理":"1.如遇到天災\/人員受傷或不適時,全隊依原路徑折返2.全隊保有旅遊平安險3.全隊配有急救包4.全隊都留緊急連絡人(如附件)"},"members":[["1","連朱建霖","A120511318","&nbsp;","63-05-21","台中市神岡區光啟路247巷19號","0935-310365"," 朱維龍 "," 0910220277 "],["2","陳勝鳳","L221217954","&nbsp;","63-12-14","台中市神岡區光啟路247巷20號","0917-196028"," 朱維龍 "," 0910220277 "],["3","林沛蓉","L222626297","&nbsp;","64-09-28","台中市豐原區社皮路76巷21號5樓","0915668198"," 黃思蒨 "," 0938639124 "],["4","蔡文明","M120249013","&nbsp;","58-09-01","台中市潭子區復興路1段50巷13弄2-1","0923288608"," 蔡流玉子 "," 04-25388149 "],["5","盧彥良","L123150898","&nbsp;","72-07-17","台中市豐原區南陽路123巷29弄40號","0910523593"," 盧玟伃 "," 0937036882 "],["6","鮑貞汝","L222435572","&nbsp;","69-12-24","台中市豐原區富陽路129號","0972058325"," 鮑美羽 "," 0933191313 "]],"reviewed":{"check_note":""},"attachment":["R10700624-2018-01-30-22-25-19-2101061624.xls"]}